setup.py
anomaly_detection/__init__.py
anomaly_detection/anomaly_detect_ts.py
anomaly_detection/anomaly_detect_vec.py
anomaly_detection/dynamic_cusum.py
haven_anomaly_detection.egg-info/PKG-INFO
haven_anomaly_detection.egg-info/SOURCES.txt
haven_anomaly_detection.egg-info/dependency_links.txt
haven_anomaly_detection.egg-info/requires.txt
haven_anomaly_detection.egg-info/top_level.txt