Metadata-Version: 1.0
Name: haven-anomaly-detection
Version: 0.0.3
Summary: A python implementation of https://github.com/twitter/AnomalyDetection
Home-page: UNKNOWN
Author: UNKNOWN
Author-email: UNKNOWN
License: UNKNOWN
Platform: UNKNOWN
